{
  "m_ObjectHideFlags": 0,
  "m_CorrespondingSourceObject": {
    "fileID": 0
  },
  "m_PrefabInstance": {
    "fileID": 0
  },
  "m_PrefabAsset": {
    "fileID": 0
  },
  "m_GameObject": {
    "fileID": 0
  },
  "m_Enabled": 1,
  "m_EditorHideFlags": 0,
  "m_Script": {
    "fileID": 11500000,
    "guid": "d22e55d88a56a9cc174a4379c66bb9c6",
    "type": 3
  },
  "m_Name": "Level 966",
  "m_EditorClassIdentifier": null,
  "categories": [
    {
      "category": "polo",
      "parentCategory": "equestrian",
      "icon": null,
      "words": [
        {
          "fullWord": "mallet",
          "icon": null,
          "IsCracked": 0,
          "crackBreakNum": 0,
          "IsLinked": 0,
          "linkedChunkWords": []
        },
        {
          "fullWord": "chukker",
          "icon": null,
          "IsCracked": 0,
          "crackBreakNum": 0,
          "IsLinked": 0,
          "linkedChunkWords": []
        },
        {
          "fullWord": "divot",
          "icon": null,
          "IsCracked": 0,
          "crackBreakNum": 0,
          "IsLinked": 0,
          "linkedChunkWords": []
        },
        {
          "fullWord": "pony",
          "icon": null,
          "IsCracked": 0,
          "crackBreakNum": 0,
          "IsLinked": 0,
          "linkedChunkWords": []
        }
      ]
    },
    {
      "category": "jolly roger",
      "parentCategory": null,
      "icon": null,
      "words": [
        {
          "fullWord": "black",
          "icon": null,
          "IsCracked": 0,
          "crackBreakNum": 0,
          "IsLinked": 0,
          "linkedChunkWords": []
        },
        {
          "fullWord": "bones",
          "icon": null,
          "IsCracked": 0,
          "crackBreakNum": 0,
          "IsLinked": 0,
          "linkedChunkWords": []
        },
        {
          "fullWord": "skull",
          "icon": null,
          "IsCracked": 0,
          "crackBreakNum": 0,
          "IsLinked": 0,
          "linkedChunkWords": []
        },
        {
          "fullWord": "crossbones",
          "icon": null,
          "IsCracked": 0,
          "crackBreakNum": 0,
          "IsLinked": 0,
          "linkedChunkWords": []
        }
      ]
    },
    {
      "category": "olympics",
      "parentCategory": "greece",
      "icon": null,
      "words": [
        {
          "fullWord": "torch",
          "icon": null,
          "IsCracked": 0,
          "crackBreakNum": 0,
          "IsLinked": 0,
          "linkedChunkWords": []
        },
        {
          "fullWord": "rings",
          "icon": null,
          "IsCracked": 0,
          "crackBreakNum": 0,
          "IsLinked": 0,
          "linkedChunkWords": []
        },
        {
          "fullWord": "medal",
          "icon": null,
          "IsCracked": 0,
          "crackBreakNum": 0,
          "IsLinked": 0,
          "linkedChunkWords": []
        },
        {
          "fullWord": "equestrian",
          "icon": null,
          "IsCracked": 0,
          "crackBreakNum": 0,
          "IsLinked": 0,
          "linkedChunkWords": []
        }
      ]
    },
    {
      "category": "underground harvest",
      "parentCategory": null,
      "icon": null,
      "words": [
        {
          "fullWord": "beet",
          "icon": null,
          "IsCracked": 0,
          "crackBreakNum": 0,
          "IsLinked": 0,
          "linkedChunkWords": []
        },
        {
          "fullWord": "carrot",
          "icon": null,
          "IsCracked": 0,
          "crackBreakNum": 0,
          "IsLinked": 0,
          "linkedChunkWords": []
        },
        {
          "fullWord": "radish",
          "icon": null,
          "IsCracked": 0,
          "crackBreakNum": 0,
          "IsLinked": 0,
          "linkedChunkWords": []
        },
        {
          "fullWord": "turnip",
          "icon": null,
          "IsCracked": 0,
          "crackBreakNum": 0,
          "IsLinked": 0,
          "linkedChunkWords": []
        }
      ]
    },
    {
      "category": "equestrian",
      "parentCategory": "olympics",
      "icon": null,
      "words": [
        {
          "fullWord": "polo",
          "icon": null,
          "IsCracked": 0,
          "crackBreakNum": 0,
          "IsLinked": 0,
          "linkedChunkWords": []
        },
        {
          "fullWord": "dressage",
          "icon": null,
          "IsCracked": 0,
          "crackBreakNum": 0,
          "IsLinked": 0,
          "linkedChunkWords": []
        },
        {
          "fullWord": "show",
          "icon": null,
          "IsCracked": 0,
          "crackBreakNum": 0,
          "IsLinked": 0,
          "linkedChunkWords": []
        },
        {
          "fullWord": "eventing",
          "icon": null,
          "IsCracked": 0,
          "crackBreakNum": 0,
          "IsLinked": 0,
          "linkedChunkWords": []
        }
      ]
    },
    {
      "category": "brazilian culture",
      "parentCategory": null,
      "icon": null,
      "words": [
        {
          "fullWord": "samba",
          "icon": null,
          "IsCracked": 0,
          "crackBreakNum": 0,
          "IsLinked": 0,
          "linkedChunkWords": []
        },
        {
          "fullWord": "capoeira",
          "icon": null,
          "IsCracked": 0,
          "crackBreakNum": 0,
          "IsLinked": 0,
          "linkedChunkWords": []
        },
        {
          "fullWord": "carnaval",
          "icon": null,
          "IsCracked": 0,
          "crackBreakNum": 0,
          "IsLinked": 0,
          "linkedChunkWords": []
        },
        {
          "fullWord": "favelas",
          "icon": null,
          "IsCracked": 0,
          "crackBreakNum": 0,
          "IsLinked": 0,
          "linkedChunkWords": []
        }
      ]
    },
    {
      "category": "greece",
      "parentCategory": null,
      "icon": null,
      "words": [
        {
          "fullWord": "athens",
          "icon": null,
          "IsCracked": 0,
          "crackBreakNum": 0,
          "IsLinked": 0,
          "linkedChunkWords": []
        },
        {
          "fullWord": "myths",
          "icon": null,
          "IsCracked": 0,
          "crackBreakNum": 0,
          "IsLinked": 0,
          "linkedChunkWords": []
        },
        {
          "fullWord": "olympics",
          "icon": null,
          "IsCracked": 0,
          "crackBreakNum": 0,
          "IsLinked": 0,
          "linkedChunkWords": []
        },
        {
          "fullWord": "olive",
          "icon": null,
          "IsCracked": 0,
          "crackBreakNum": 0,
          "IsLinked": 0,
          "linkedChunkWords": []
        }
      ]
    },
    {
      "category": "striped animals",
      "parentCategory": null,
      "icon": null,
      "words": [
        {
          "fullWord": "bee",
          "icon": null,
          "IsCracked": 0,
          "crackBreakNum": 0,
          "IsLinked": 0,
          "linkedChunkWords": []
        },
        {
          "fullWord": "chipmunk",
          "icon": null,
          "IsCracked": 0,
          "crackBreakNum": 0,
          "IsLinked": 0,
          "linkedChunkWords": []
        },
        {
          "fullWord": "clownfish",
          "icon": null,
          "IsCracked": 0,
          "crackBreakNum": 0,
          "IsLinked": 0,
          "linkedChunkWords": []
        },
        {
          "fullWord": "okapi",
          "icon": null,
          "IsCracked": 0,
          "crackBreakNum": 0,
          "IsLinked": 0,
          "linkedChunkWords": []
        }
      ]
    },
    {
      "category": "beastly",
      "parentCategory": null,
      "icon": null,
      "words": [
        {
          "fullWord": "brutish",
          "icon": null,
          "IsCracked": 0,
          "crackBreakNum": 0,
          "IsLinked": 0,
          "linkedChunkWords": []
        },
        {
          "fullWord": "primal",
          "icon": null,
          "IsCracked": 0,
          "crackBreakNum": 0,
          "IsLinked": 0,
          "linkedChunkWords": []
        },
        {
          "fullWord": "vicious",
          "icon": null,
          "IsCracked": 0,
          "crackBreakNum": 0,
          "IsLinked": 0,
          "linkedChunkWords": []
        },
        {
          "fullWord": "savage",
          "icon": null,
          "IsCracked": 0,
          "crackBreakNum": 0,
          "IsLinked": 0,
          "linkedChunkWords": []
        }
      ]
    },
    {
      "category": "hatred",
      "parentCategory": null,
      "icon": null,
      "words": [
        {
          "fullWord": "abhor",
          "icon": null,
          "IsCracked": 0,
          "crackBreakNum": 0,
          "IsLinked": 0,
          "linkedChunkWords": []
        },
        {
          "fullWord": "despise",
          "icon": null,
          "IsCracked": 0,
          "crackBreakNum": 0,
          "IsLinked": 0,
          "linkedChunkWords": []
        },
        {
          "fullWord": "loathe",
          "icon": null,
          "IsCracked": 0,
          "crackBreakNum": 0,
          "IsLinked": 0,
          "linkedChunkWords": []
        },
        {
          "fullWord": "resent",
          "icon": null,
          "IsCracked": 0,
          "crackBreakNum": 0,
          "IsLinked": 0,
          "linkedChunkWords": []
        }
      ]
    }
  ],
  "maxBubblesInScene": 24,
  "moveLimit": 10,
  "randomSeed": 0,
  "levelDifficulty": 0,
  "allWordEntries": [
    {
      "fullWord": "mallet",
      "icon": null,
      "IsCracked": 0,
      "crackBreakNum": 0,
      "IsLinked": 0,
      "linkedChunkWords": [],
      "parentWord": null
    },
    {
      "fullWord": "chukker",
      "icon": null,
      "IsCracked": 0,
      "crackBreakNum": 0,
      "IsLinked": 0,
      "linkedChunkWords": [],
      "parentWord": null
    },
    {
      "fullWord": "divot",
      "icon": null,
      "IsCracked": 0,
      "crackBreakNum": 0,
      "IsLinked": 0,
      "linkedChunkWords": [],
      "parentWord": null
    },
    {
      "fullWord": "pony",
      "icon": null,
      "IsCracked": 0,
      "crackBreakNum": 0,
      "IsLinked": 0,
      "linkedChunkWords": [],
      "parentWord": null
    },
    {
      "fullWord": "black",
      "icon": null,
      "IsCracked": 0,
      "crackBreakNum": 0,
      "IsLinked": 0,
      "linkedChunkWords": [],
      "parentWord": null
    },
    {
      "fullWord": "bones",
      "icon": null,
      "IsCracked": 0,
      "crackBreakNum": 0,
      "IsLinked": 0,
      "linkedChunkWords": [],
      "parentWord": null
    },
    {
      "fullWord": "skull",
      "icon": null,
      "IsCracked": 0,
      "crackBreakNum": 0,
      "IsLinked": 0,
      "linkedChunkWords": [],
      "parentWord": null
    },
    {
      "fullWord": "crossbones",
      "icon": null,
      "IsCracked": 0,
      "crackBreakNum": 0,
      "IsLinked": 0,
      "linkedChunkWords": [],
      "parentWord": null
    },
    {
      "fullWord": "Tor",
      "icon": null,
      "IsCracked": 0,
      "crackBreakNum": 0,
      "IsLinked": 0,
      "linkedChunkWords": [],
      "parentWord": "Torch"
    },
    {
      "fullWord": "Ch",
      "icon": null,
      "IsCracked": 0,
      "crackBreakNum": 0,
      "IsLinked": 0,
      "linkedChunkWords": [],
      "parentWord": "Torch"
    },
    {
      "fullWord": "rings",
      "icon": null,
      "IsCracked": 0,
      "crackBreakNum": 0,
      "IsLinked": 0,
      "linkedChunkWords": [],
      "parentWord": null
    },
    {
      "fullWord": "Me",
      "icon": null,
      "IsCracked": 0,
      "crackBreakNum": 0,
      "IsLinked": 0,
      "linkedChunkWords": [],
      "parentWord": "Medal"
    },
    {
      "fullWord": "Dal",
      "icon": null,
      "IsCracked": 0,
      "crackBreakNum": 0,
      "IsLinked": 0,
      "linkedChunkWords": [],
      "parentWord": "Medal"
    },
    {
      "fullWord": "beet",
      "icon": null,
      "IsCracked": 0,
      "crackBreakNum": 0,
      "IsLinked": 0,
      "linkedChunkWords": [],
      "parentWord": null
    },
    {
      "fullWord": "carrot",
      "icon": null,
      "IsCracked": 0,
      "crackBreakNum": 0,
      "IsLinked": 0,
      "linkedChunkWords": [],
      "parentWord": null
    },
    {
      "fullWord": "radish",
      "icon": null,
      "IsCracked": 0,
      "crackBreakNum": 0,
      "IsLinked": 0,
      "linkedChunkWords": [],
      "parentWord": null
    },
    {
      "fullWord": "turnip",
      "icon": null,
      "IsCracked": 0,
      "crackBreakNum": 0,
      "IsLinked": 0,
      "linkedChunkWords": [],
      "parentWord": null
    },
    {
      "fullWord": "dressage",
      "icon": null,
      "IsCracked": 0,
      "crackBreakNum": 0,
      "IsLinked": 0,
      "linkedChunkWords": [],
      "parentWord": null
    },
    {
      "fullWord": "Sh",
      "icon": null,
      "IsCracked": 0,
      "crackBreakNum": 0,
      "IsLinked": 0,
      "linkedChunkWords": [],
      "parentWord": "Show"
    },
    {
      "fullWord": "Ow",
      "icon": null,
      "IsCracked": 0,
      "crackBreakNum": 0,
      "IsLinked": 0,
      "linkedChunkWords": [],
      "parentWord": "Show"
    },
    {
      "fullWord": "eventing",
      "icon": null,
      "IsCracked": 0,
      "crackBreakNum": 0,
      "IsLinked": 0,
      "linkedChunkWords": [],
      "parentWord": null
    },
    {
      "fullWord": "samba",
      "icon": null,
      "IsCracked": 0,
      "crackBreakNum": 0,
      "IsLinked": 0,
      "linkedChunkWords": [],
      "parentWord": null
    },
    {
      "fullWord": "capoeira",
      "icon": null,
      "IsCracked": 0,
      "crackBreakNum": 0,
      "IsLinked": 0,
      "linkedChunkWords": [],
      "parentWord": null
    },
    {
      "fullWord": "carnaval",
      "icon": null,
      "IsCracked": 0,
      "crackBreakNum": 0,
      "IsLinked": 0,
      "linkedChunkWords": [],
      "parentWord": null
    },
    {
      "fullWord": "favelas",
      "icon": null,
      "IsCracked": 0,
      "crackBreakNum": 0,
      "IsLinked": 0,
      "linkedChunkWords": [],
      "parentWord": null
    },
    {
      "fullWord": "athens",
      "icon": null,
      "IsCracked": 0,
      "crackBreakNum": 0,
      "IsLinked": 0,
      "linkedChunkWords": [],
      "parentWord": null
    },
    {
      "fullWord": "myths",
      "icon": null,
      "IsCracked": 0,
      "crackBreakNum": 0,
      "IsLinked": 0,
      "linkedChunkWords": [],
      "parentWord": null
    },
    {
      "fullWord": "Oli",
      "icon": null,
      "IsCracked": 0,
      "crackBreakNum": 0,
      "IsLinked": 0,
      "linkedChunkWords": [],
      "parentWord": "Olive"
    },
    {
      "fullWord": "Ve",
      "icon": null,
      "IsCracked": 0,
      "crackBreakNum": 0,
      "IsLinked": 0,
      "linkedChunkWords": [],
      "parentWord": "Olive"
    },
    {
      "fullWord": "bee",
      "icon": null,
      "IsCracked": 0,
      "crackBreakNum": 0,
      "IsLinked": 0,
      "linkedChunkWords": [],
      "parentWord": null
    },
    {
      "fullWord": "chipmunk",
      "icon": null,
      "IsCracked": 0,
      "crackBreakNum": 0,
      "IsLinked": 0,
      "linkedChunkWords": [],
      "parentWord": null
    },
    {
      "fullWord": "clownfish",
      "icon": null,
      "IsCracked": 0,
      "crackBreakNum": 0,
      "IsLinked": 0,
      "linkedChunkWords": [],
      "parentWord": null
    },
    {
      "fullWord": "okapi",
      "icon": null,
      "IsCracked": 0,
      "crackBreakNum": 0,
      "IsLinked": 0,
      "linkedChunkWords": [],
      "parentWord": null
    },
    {
      "fullWord": "brutish",
      "icon": null,
      "IsCracked": 0,
      "crackBreakNum": 0,
      "IsLinked": 0,
      "linkedChunkWords": [],
      "parentWord": null
    },
    {
      "fullWord": "primal",
      "icon": null,
      "IsCracked": 0,
      "crackBreakNum": 0,
      "IsLinked": 0,
      "linkedChunkWords": [],
      "parentWord": null
    },
    {
      "fullWord": "vicious",
      "icon": null,
      "IsCracked": 0,
      "crackBreakNum": 0,
      "IsLinked": 0,
      "linkedChunkWords": [],
      "parentWord": null
    },
    {
      "fullWord": "savage",
      "icon": null,
      "IsCracked": 0,
      "crackBreakNum": 0,
      "IsLinked": 0,
      "linkedChunkWords": [],
      "parentWord": null
    },
    {
      "fullWord": "abhor",
      "icon": null,
      "IsCracked": 0,
      "crackBreakNum": 0,
      "IsLinked": 0,
      "linkedChunkWords": [],
      "parentWord": null
    },
    {
      "fullWord": "despise",
      "icon": null,
      "IsCracked": 0,
      "crackBreakNum": 0,
      "IsLinked": 0,
      "linkedChunkWords": [],
      "parentWord": null
    },
    {
      "fullWord": "loathe",
      "icon": null,
      "IsCracked": 0,
      "crackBreakNum": 0,
      "IsLinked": 0,
      "linkedChunkWords": [],
      "parentWord": null
    },
    {
      "fullWord": "resent",
      "icon": null,
      "IsCracked": 0,
      "crackBreakNum": 0,
      "IsLinked": 0,
      "linkedChunkWords": [],
      "parentWord": null
    }
  ],
  "allWords": [],
  "frozenBubbles": [],
  "burstBubbles": [],
  "keyLockBubbles": [],
  "bubbleChains": [],
  "useBubbleSeparator": 0,
  "bubbleSeparatorData": {
    "breakThreshold": 3,
    "linkedWords": []
  },
  "crypticBubbles": [],
  "screwLockBubbles": [],
  "backwardBubbles": [],
  "crackedBubbles": [],
  "linkedBubbles": []
}