{
  "m_ObjectHideFlags": 0,
  "m_CorrespondingSourceObject": {
    "fileID": 0
  },
  "m_PrefabInstance": {
    "fileID": 0
  },
  "m_PrefabAsset": {
    "fileID": 0
  },
  "m_GameObject": {
    "fileID": 0
  },
  "m_Enabled": 1,
  "m_EditorHideFlags": 0,
  "m_Script": {
    "fileID": 11500000,
    "guid": "d22e55d88a56a9cc174a4379c66bb9c6",
    "type": 3
  },
  "m_Name": "Level 315",
  "m_EditorClassIdentifier": null,
  "categories": [
    {
      "category": "traps",
      "parentCategory": null,
      "icon": null,
      "words": [
        {
          "fullWord": "cage",
          "icon": null,
          "IsCracked": 0,
          "crackBreakNum": 0,
          "IsLinked": 0,
          "linkedChunkWords": []
        },
        {
          "fullWord": "pitfall",
          "icon": null,
          "IsCracked": 0,
          "crackBreakNum": 0,
          "IsLinked": 0,
          "linkedChunkWords": []
        },
        {
          "fullWord": "trapwire",
          "icon": null,
          "IsCracked": 0,
          "crackBreakNum": 0,
          "IsLinked": 0,
          "linkedChunkWords": []
        },
        {
          "fullWord": "snare",
          "icon": null,
          "IsCracked": 0,
          "crackBreakNum": 0,
          "IsLinked": 0,
          "linkedChunkWords": []
        }
      ]
    },
    {
      "category": "organizations",
      "parentCategory": null,
      "icon": null,
      "words": [
        {
          "fullWord": "guild",
          "icon": null,
          "IsCracked": 0,
          "crackBreakNum": 0,
          "IsLinked": 0,
          "linkedChunkWords": []
        },
        {
          "fullWord": "clan",
          "icon": null,
          "IsCracked": 0,
          "crackBreakNum": 0,
          "IsLinked": 0,
          "linkedChunkWords": []
        },
        {
          "fullWord": "house",
          "icon": null,
          "IsCracked": 0,
          "crackBreakNum": 0,
          "IsLinked": 0,
          "linkedChunkWords": []
        },
        {
          "fullWord": "tribe",
          "icon": null,
          "IsCracked": 0,
          "crackBreakNum": 0,
          "IsLinked": 0,
          "linkedChunkWords": []
        }
      ]
    },
    {
      "category": "creative hobbies",
      "parentCategory": null,
      "icon": null,
      "words": [
        {
          "fullWord": "knitting",
          "icon": null,
          "IsCracked": 0,
          "crackBreakNum": 0,
          "IsLinked": 0,
          "linkedChunkWords": []
        },
        {
          "fullWord": "painting",
          "icon": null,
          "IsCracked": 0,
          "crackBreakNum": 0,
          "IsLinked": 0,
          "linkedChunkWords": []
        },
        {
          "fullWord": "dancing",
          "icon": null,
          "IsCracked": 0,
          "crackBreakNum": 0,
          "IsLinked": 0,
          "linkedChunkWords": []
        },
        {
          "fullWord": "crocheting",
          "icon": null,
          "IsCracked": 0,
          "crackBreakNum": 0,
          "IsLinked": 0,
          "linkedChunkWords": []
        }
      ]
    },
    {
      "category": "flea market",
      "parentCategory": null,
      "icon": null,
      "words": [
        {
          "fullWord": "bargain",
          "icon": null,
          "IsCracked": 0,
          "crackBreakNum": 0,
          "IsLinked": 0,
          "linkedChunkWords": []
        },
        {
          "fullWord": "knickknack",
          "icon": null,
          "IsCracked": 0,
          "crackBreakNum": 0,
          "IsLinked": 0,
          "linkedChunkWords": []
        },
        {
          "fullWord": "haggle",
          "icon": null,
          "IsCracked": 0,
          "crackBreakNum": 0,
          "IsLinked": 0,
          "linkedChunkWords": []
        },
        {
          "fullWord": "sale",
          "icon": null,
          "IsCracked": 0,
          "crackBreakNum": 0,
          "IsLinked": 0,
          "linkedChunkWords": []
        }
      ]
    },
    {
      "category": "marine",
      "parentCategory": null,
      "icon": null,
      "words": [
        {
          "fullWord": "coral",
          "icon": null,
          "IsCracked": 0,
          "crackBreakNum": 0,
          "IsLinked": 0,
          "linkedChunkWords": []
        },
        {
          "fullWord": "shark",
          "icon": null,
          "IsCracked": 0,
          "crackBreakNum": 0,
          "IsLinked": 0,
          "linkedChunkWords": []
        },
        {
          "fullWord": "turtle",
          "icon": null,
          "IsCracked": 0,
          "crackBreakNum": 0,
          "IsLinked": 0,
          "linkedChunkWords": []
        },
        {
          "fullWord": "seahorse",
          "icon": null,
          "IsCracked": 0,
          "crackBreakNum": 0,
          "IsLinked": 0,
          "linkedChunkWords": []
        }
      ]
    },
    {
      "category": "echo",
      "parentCategory": null,
      "icon": null,
      "words": [
        {
          "fullWord": "reverb",
          "icon": null,
          "IsCracked": 0,
          "crackBreakNum": 0,
          "IsLinked": 0,
          "linkedChunkWords": []
        },
        {
          "fullWord": "sound",
          "icon": null,
          "IsCracked": 0,
          "crackBreakNum": 0,
          "IsLinked": 0,
          "linkedChunkWords": []
        },
        {
          "fullWord": "repeat",
          "icon": null,
          "IsCracked": 0,
          "crackBreakNum": 0,
          "IsLinked": 0,
          "linkedChunkWords": []
        },
        {
          "fullWord": "reflection",
          "icon": null,
          "IsCracked": 0,
          "crackBreakNum": 0,
          "IsLinked": 0,
          "linkedChunkWords": []
        }
      ]
    },
    {
      "category": "masks",
      "parentCategory": null,
      "icon": null,
      "words": [
        {
          "fullWord": "visor",
          "icon": null,
          "IsCracked": 0,
          "crackBreakNum": 0,
          "IsLinked": 0,
          "linkedChunkWords": []
        },
        {
          "fullWord": "veil",
          "icon": null,
          "IsCracked": 0,
          "crackBreakNum": 0,
          "IsLinked": 0,
          "linkedChunkWords": []
        },
        {
          "fullWord": "facade",
          "icon": null,
          "IsCracked": 0,
          "crackBreakNum": 0,
          "IsLinked": 0,
          "linkedChunkWords": []
        },
        {
          "fullWord": "disguise",
          "icon": null,
          "IsCracked": 0,
          "crackBreakNum": 0,
          "IsLinked": 0,
          "linkedChunkWords": []
        }
      ]
    },
    {
      "category": "zodiac",
      "parentCategory": null,
      "icon": null,
      "words": [
        {
          "fullWord": "fish",
          "icon": null,
          "IsCracked": 0,
          "crackBreakNum": 0,
          "IsLinked": 0,
          "linkedChunkWords": []
        },
        {
          "fullWord": "goat",
          "icon": null,
          "IsCracked": 0,
          "crackBreakNum": 0,
          "IsLinked": 0,
          "linkedChunkWords": []
        },
        {
          "fullWord": "scales",
          "icon": null,
          "IsCracked": 0,
          "crackBreakNum": 0,
          "IsLinked": 0,
          "linkedChunkWords": []
        },
        {
          "fullWord": "twins",
          "icon": null,
          "IsCracked": 0,
          "crackBreakNum": 0,
          "IsLinked": 0,
          "linkedChunkWords": []
        }
      ]
    },
    {
      "category": "fruit",
      "parentCategory": null,
      "icon": null,
      "words": [
        {
          "fullWord": "date",
          "icon": null,
          "IsCracked": 0,
          "crackBreakNum": 0,
          "IsLinked": 0,
          "linkedChunkWords": []
        },
        {
          "fullWord": "kiwi",
          "icon": null,
          "IsCracked": 0,
          "crackBreakNum": 0,
          "IsLinked": 0,
          "linkedChunkWords": []
        },
        {
          "fullWord": "lemon",
          "icon": null,
          "IsCracked": 0,
          "crackBreakNum": 0,
          "IsLinked": 0,
          "linkedChunkWords": []
        },
        {
          "fullWord": "orange",
          "icon": null,
          "IsCracked": 0,
          "crackBreakNum": 0,
          "IsLinked": 0,
          "linkedChunkWords": []
        }
      ]
    },
    {
      "category": "birds",
      "parentCategory": null,
      "icon": null,
      "words": [
        {
          "fullWord": "crane",
          "icon": null,
          "IsCracked": 0,
          "crackBreakNum": 0,
          "IsLinked": 0,
          "linkedChunkWords": []
        },
        {
          "fullWord": "jay",
          "icon": null,
          "IsCracked": 0,
          "crackBreakNum": 0,
          "IsLinked": 0,
          "linkedChunkWords": []
        },
        {
          "fullWord": "swallow",
          "icon": null,
          "IsCracked": 0,
          "crackBreakNum": 0,
          "IsLinked": 0,
          "linkedChunkWords": []
        },
        {
          "fullWord": "turkey",
          "icon": null,
          "IsCracked": 0,
          "crackBreakNum": 0,
          "IsLinked": 0,
          "linkedChunkWords": []
        }
      ]
    }
  ],
  "maxBubblesInScene": 24,
  "moveLimit": 10,
  "randomSeed": 0,
  "levelDifficulty": 0,
  "allWordEntries": [
    {
      "fullWord": "cage",
      "icon": null,
      "IsCracked": 0,
      "crackBreakNum": 0,
      "IsLinked": 0,
      "linkedChunkWords": [],
      "parentWord": null
    },
    {
      "fullWord": "pitfall",
      "icon": null,
      "IsCracked": 0,
      "crackBreakNum": 0,
      "IsLinked": 0,
      "linkedChunkWords": [],
      "parentWord": null
    },
    {
      "fullWord": "trapwire",
      "icon": null,
      "IsCracked": 0,
      "crackBreakNum": 0,
      "IsLinked": 0,
      "linkedChunkWords": [],
      "parentWord": null
    },
    {
      "fullWord": "snare",
      "icon": null,
      "IsCracked": 0,
      "crackBreakNum": 0,
      "IsLinked": 0,
      "linkedChunkWords": [],
      "parentWord": null
    },
    {
      "fullWord": "guild",
      "icon": null,
      "IsCracked": 0,
      "crackBreakNum": 0,
      "IsLinked": 0,
      "linkedChunkWords": [],
      "parentWord": null
    },
    {
      "fullWord": "clan",
      "icon": null,
      "IsCracked": 0,
      "crackBreakNum": 0,
      "IsLinked": 0,
      "linkedChunkWords": [],
      "parentWord": null
    },
    {
      "fullWord": "house",
      "icon": null,
      "IsCracked": 0,
      "crackBreakNum": 0,
      "IsLinked": 0,
      "linkedChunkWords": [],
      "parentWord": null
    },
    {
      "fullWord": "tribe",
      "icon": null,
      "IsCracked": 0,
      "crackBreakNum": 0,
      "IsLinked": 0,
      "linkedChunkWords": [],
      "parentWord": null
    },
    {
      "fullWord": "knitting",
      "icon": null,
      "IsCracked": 0,
      "crackBreakNum": 0,
      "IsLinked": 0,
      "linkedChunkWords": [],
      "parentWord": null
    },
    {
      "fullWord": "painting",
      "icon": null,
      "IsCracked": 0,
      "crackBreakNum": 0,
      "IsLinked": 0,
      "linkedChunkWords": [],
      "parentWord": null
    },
    {
      "fullWord": "dancing",
      "icon": null,
      "IsCracked": 0,
      "crackBreakNum": 0,
      "IsLinked": 0,
      "linkedChunkWords": [],
      "parentWord": null
    },
    {
      "fullWord": "Cro",
      "icon": null,
      "IsCracked": 0,
      "crackBreakNum": 0,
      "IsLinked": 0,
      "linkedChunkWords": [],
      "parentWord": "Crocheting"
    },
    {
      "fullWord": "Cheting",
      "icon": null,
      "IsCracked": 0,
      "crackBreakNum": 0,
      "IsLinked": 0,
      "linkedChunkWords": [],
      "parentWord": "Crocheting"
    },
    {
      "fullWord": "bargain",
      "icon": null,
      "IsCracked": 0,
      "crackBreakNum": 0,
      "IsLinked": 0,
      "linkedChunkWords": [],
      "parentWord": null
    },
    {
      "fullWord": "Knick",
      "icon": null,
      "IsCracked": 0,
      "crackBreakNum": 0,
      "IsLinked": 0,
      "linkedChunkWords": [],
      "parentWord": "Knickknack"
    },
    {
      "fullWord": "Knack",
      "icon": null,
      "IsCracked": 0,
      "crackBreakNum": 0,
      "IsLinked": 0,
      "linkedChunkWords": [],
      "parentWord": "Knickknack"
    },
    {
      "fullWord": "haggle",
      "icon": null,
      "IsCracked": 0,
      "crackBreakNum": 0,
      "IsLinked": 0,
      "linkedChunkWords": [],
      "parentWord": null
    },
    {
      "fullWord": "sale",
      "icon": null,
      "IsCracked": 0,
      "crackBreakNum": 0,
      "IsLinked": 0,
      "linkedChunkWords": [],
      "parentWord": null
    },
    {
      "fullWord": "coral",
      "icon": null,
      "IsCracked": 0,
      "crackBreakNum": 0,
      "IsLinked": 0,
      "linkedChunkWords": [],
      "parentWord": null
    },
    {
      "fullWord": "shark",
      "icon": null,
      "IsCracked": 0,
      "crackBreakNum": 0,
      "IsLinked": 0,
      "linkedChunkWords": [],
      "parentWord": null
    },
    {
      "fullWord": "turtle",
      "icon": null,
      "IsCracked": 0,
      "crackBreakNum": 0,
      "IsLinked": 0,
      "linkedChunkWords": [],
      "parentWord": null
    },
    {
      "fullWord": "Sea",
      "icon": null,
      "IsCracked": 0,
      "crackBreakNum": 0,
      "IsLinked": 0,
      "linkedChunkWords": [],
      "parentWord": "Seahorse"
    },
    {
      "fullWord": "Horse",
      "icon": null,
      "IsCracked": 0,
      "crackBreakNum": 0,
      "IsLinked": 0,
      "linkedChunkWords": [],
      "parentWord": "Seahorse"
    },
    {
      "fullWord": "reverb",
      "icon": null,
      "IsCracked": 0,
      "crackBreakNum": 0,
      "IsLinked": 0,
      "linkedChunkWords": [],
      "parentWord": null
    },
    {
      "fullWord": "sound",
      "icon": null,
      "IsCracked": 0,
      "crackBreakNum": 0,
      "IsLinked": 0,
      "linkedChunkWords": [],
      "parentWord": null
    },
    {
      "fullWord": "repeat",
      "icon": null,
      "IsCracked": 0,
      "crackBreakNum": 0,
      "IsLinked": 0,
      "linkedChunkWords": [],
      "parentWord": null
    },
    {
      "fullWord": "reflection",
      "icon": null,
      "IsCracked": 0,
      "crackBreakNum": 0,
      "IsLinked": 0,
      "linkedChunkWords": [],
      "parentWord": null
    },
    {
      "fullWord": "visor",
      "icon": null,
      "IsCracked": 0,
      "crackBreakNum": 0,
      "IsLinked": 0,
      "linkedChunkWords": [],
      "parentWord": null
    },
    {
      "fullWord": "veil",
      "icon": null,
      "IsCracked": 0,
      "crackBreakNum": 0,
      "IsLinked": 0,
      "linkedChunkWords": [],
      "parentWord": null
    },
    {
      "fullWord": "facade",
      "icon": null,
      "IsCracked": 0,
      "crackBreakNum": 0,
      "IsLinked": 0,
      "linkedChunkWords": [],
      "parentWord": null
    },
    {
      "fullWord": "disguise",
      "icon": null,
      "IsCracked": 0,
      "crackBreakNum": 0,
      "IsLinked": 0,
      "linkedChunkWords": [],
      "parentWord": null
    },
    {
      "fullWord": "fish",
      "icon": null,
      "IsCracked": 0,
      "crackBreakNum": 0,
      "IsLinked": 0,
      "linkedChunkWords": [],
      "parentWord": null
    },
    {
      "fullWord": "goat",
      "icon": null,
      "IsCracked": 0,
      "crackBreakNum": 0,
      "IsLinked": 0,
      "linkedChunkWords": [],
      "parentWord": null
    },
    {
      "fullWord": "scales",
      "icon": null,
      "IsCracked": 0,
      "crackBreakNum": 0,
      "IsLinked": 0,
      "linkedChunkWords": [],
      "parentWord": null
    },
    {
      "fullWord": "twins",
      "icon": null,
      "IsCracked": 0,
      "crackBreakNum": 0,
      "IsLinked": 0,
      "linkedChunkWords": [],
      "parentWord": null
    },
    {
      "fullWord": "date",
      "icon": null,
      "IsCracked": 0,
      "crackBreakNum": 0,
      "IsLinked": 0,
      "linkedChunkWords": [],
      "parentWord": null
    },
    {
      "fullWord": "kiwi",
      "icon": null,
      "IsCracked": 0,
      "crackBreakNum": 0,
      "IsLinked": 0,
      "linkedChunkWords": [],
      "parentWord": null
    },
    {
      "fullWord": "lemon",
      "icon": null,
      "IsCracked": 0,
      "crackBreakNum": 0,
      "IsLinked": 0,
      "linkedChunkWords": [],
      "parentWord": null
    },
    {
      "fullWord": "orange",
      "icon": null,
      "IsCracked": 0,
      "crackBreakNum": 0,
      "IsLinked": 0,
      "linkedChunkWords": [],
      "parentWord": null
    },
    {
      "fullWord": "crane",
      "icon": null,
      "IsCracked": 0,
      "crackBreakNum": 0,
      "IsLinked": 0,
      "linkedChunkWords": [],
      "parentWord": null
    },
    {
      "fullWord": "jay",
      "icon": null,
      "IsCracked": 0,
      "crackBreakNum": 0,
      "IsLinked": 0,
      "linkedChunkWords": [],
      "parentWord": null
    },
    {
      "fullWord": "swallow",
      "icon": null,
      "IsCracked": 0,
      "crackBreakNum": 0,
      "IsLinked": 0,
      "linkedChunkWords": [],
      "parentWord": null
    },
    {
      "fullWord": "turkey",
      "icon": null,
      "IsCracked": 0,
      "crackBreakNum": 0,
      "IsLinked": 0,
      "linkedChunkWords": [],
      "parentWord": null
    }
  ],
  "allWords": [],
  "frozenBubbles": [],
  "burstBubbles": [],
  "keyLockBubbles": [],
  "bubbleChains": [],
  "useBubbleSeparator": 0,
  "bubbleSeparatorData": {
    "breakThreshold": 3,
    "linkedWords": []
  },
  "crypticBubbles": [],
  "screwLockBubbles": [
    {
      "screwLockWord": "house",
      "screwDriverWords": [
        "coral",
        "dancing",
        "turtle",
        "kiwi",
        "twins"
      ],
      "id": 0,
      "screwCount": 5
    },
    {
      "screwLockWord": "sound",
      "screwDriverWords": [
        "swallow",
        "orange",
        "turkey"
      ],
      "id": 1,
      "screwCount": 3
    }
  ],
  "backwardBubbles": [],
  "crackedBubbles": [],
  "linkedBubbles": []
}